{
  "players": [],
  "objectChanges": [
    {
      "action": "add",
      "id": "bearden_70,174",
      "name": "bearden",
      "position": [
        3496,
        15.909317058376873,
        8702.5
      ],
      "rotation": 1.1368299089574077,
      "scale": 1,
      "quality": 30,
      "lastRepairTime": 1768525531203,
      "chunkId": "chunk_70,174",
      "isBrownBearStructure": true
    },
    {
      "action": "add",
      "id": "deertree_70,174",
      "name": "deertree",
      "position": [
        3494,
        16.299944358470885,
        8699.75
      ],
      "rotation": 3.2721555700936182,
      "scale": 1,
      "quality": 100,
      "lastRepairTime": 1768525531203,
      "chunkId": "chunk_70,174",
      "isDeerTreeStructure": true
    }
  ],
  "seed": 12345
}